unbound/__init__.py
unbound/_unbound_scripts.py
unbound/py.typed
unbound/version.py
unbound/_vendor/__init__.py
unbound/_vendor/openai/__init__.py
unbound/_vendor/openai/__main__.py
unbound/_vendor/openai/_base_client.py
unbound/_vendor/openai/_client.py
unbound/_vendor/openai/_compat.py
unbound/_vendor/openai/_constants.py
unbound/_vendor/openai/_exceptions.py
unbound/_vendor/openai/_files.py
unbound/_vendor/openai/_legacy_response.py
unbound/_vendor/openai/_models.py
unbound/_vendor/openai/_module_client.py
unbound/_vendor/openai/_qs.py
unbound/_vendor/openai/_resource.py
unbound/_vendor/openai/_response.py
unbound/_vendor/openai/_streaming.py
unbound/_vendor/openai/_types.py
unbound/_vendor/openai/_version.py
unbound/_vendor/openai/pagination.py
unbound/_vendor/openai/py.typed
unbound/_vendor/openai/version.py
unbound/_vendor/openai/_extras/__init__.py
unbound/_vendor/openai/_extras/_common.py
unbound/_vendor/openai/_extras/numpy_proxy.py
unbound/_vendor/openai/_extras/pandas_proxy.py
unbound/_vendor/openai/_utils/__init__.py
unbound/_vendor/openai/_utils/_logs.py
unbound/_vendor/openai/_utils/_proxy.py
unbound/_vendor/openai/_utils/_reflection.py
unbound/_vendor/openai/_utils/_streams.py
unbound/_vendor/openai/_utils/_sync.py
unbound/_vendor/openai/_utils/_transform.py
unbound/_vendor/openai/_utils/_typing.py
unbound/_vendor/openai/_utils/_utils.py
unbound/_vendor/openai/cli/__init__.py
unbound/_vendor/openai/cli/_cli.py
unbound/_vendor/openai/cli/_errors.py
unbound/_vendor/openai/cli/_models.py
unbound/_vendor/openai/cli/_progress.py
unbound/_vendor/openai/cli/_utils.py
unbound/_vendor/openai/cli/_api/__init__.py
unbound/_vendor/openai/cli/_api/_main.py
unbound/_vendor/openai/cli/_api/audio.py
unbound/_vendor/openai/cli/_api/completions.py
unbound/_vendor/openai/cli/_api/files.py
unbound/_vendor/openai/cli/_api/image.py
unbound/_vendor/openai/cli/_api/models.py
unbound/_vendor/openai/cli/_api/chat/__init__.py
unbound/_vendor/openai/cli/_api/chat/completions.py
unbound_gateway-0.1.6.dist-info/LICENSE
unbound_gateway-0.1.6.dist-info/METADATA
unbound_gateway-0.1.6.dist-info/WHEEL
unbound_gateway-0.1.6.dist-info/entry_points.txt
unbound_gateway-0.1.6.dist-info/top_level.txt
unbound_gateway-0.1.6.dist-info/zip-safe
unbound_gateway-0.1.6.dist-info/RECORD
